dynamic_data_reduction/__init__.py
dynamic_data_reduction/coffea_dataset_tools.py
dynamic_data_reduction/ddr_coffea.py
dynamic_data_reduction/main.py
dynamic_data_reduction-2025.12.1.dist-info/licenses/LICENSE
dynamic_data_reduction-2025.12.1.dist-info/METADATA
dynamic_data_reduction-2025.12.1.dist-info/WHEEL
dynamic_data_reduction-2025.12.1.dist-info/entry_points.txt
dynamic_data_reduction-2025.12.1.dist-info/top_level.txt
dynamic_data_reduction-2025.12.1.dist-info/RECORD
