Metadata-Version: 2.4
Name: dynamic_data_reduction
Version: 2025.12.1
Summary: Dynamic MapReduce framework for data processing
Author-email: Ben Tovar <btovar@nd.edu>
Maintainer-email: Ben Tovar <btovar@nd.edu>
License-Expression: Apache-2.0
Project-URL: Homepage, https://github.com/btovar/dynamic_data_reduction
Project-URL: Repository, https://github.com/btovar/dynamic_data_reduction.git
Project-URL: Documentation, https://github.com/btovar/dynamic_data_reduction#readme
Project-URL: Bug Tracker, https://github.com/btovar/dynamic_data_reduction/issues
Keywords: mapreduce,data-processing,distributed-computing
Classifier: Development Status :: 3 - Alpha
Classifier: Intended Audience :: Developers
Classifier: Operating System :: OS Independent
Classifier: Programming Language :: Python :: 3
Classifier: Programming Language :: Python :: 3.11
Classifier: Programming Language :: Python :: 3.12
Classifier: Programming Language :: Python :: 3.13
Requires-Python: >=3.11
License-File: LICENSE
Requires-Dist: awkward>=2.8.1
Requires-Dist: coffea>=2025.3.0
Requires-Dist: fsspec>=2025.3.0
Requires-Dist: fsspec-xrootd>=0.5.1
Requires-Dist: numpy>=2.1.3
Requires-Dist: rich>=13.9.4
Requires-Dist: uproot>=5.6.0
Requires-Dist: xrootd>=5.8.1
Provides-Extra: dev
Requires-Dist: pytest>=6.0; extra == "dev"
Requires-Dist: pytest-cov>=2.0; extra == "dev"
Requires-Dist: black>=21.0; extra == "dev"
Requires-Dist: flake8>=3.8; extra == "dev"
Provides-Extra: conda
Requires-Dist: ndcctools>=7.15.8; extra == "conda"
Dynamic: license-file
